pystory/__init__.py
pystory/__main__.py
pystory/pystory.py
pystory/test_pystory.py
pystory-0.2.dist-info/DESCRIPTION.rst
pystory-0.2.dist-info/METADATA
pystory-0.2.dist-info/RECORD
pystory-0.2.dist-info/WHEEL
pystory-0.2.dist-info/entry_points.txt
pystory-0.2.dist-info/metadata.json
pystory-0.2.dist-info/top_level.txt
