Metadata-Version: 2.0
Name: pystory
Version: 0.2
Summary: A virtual environment utility for saving the commands you use in python projects.
Home-page: https://github.com/haraball/pystory
Author: Harald Kirkerød
Author-email: haraball+pystory@gmail.com
License: MIT License
